jaraco/imaging/__init__.py
jaraco/imaging/sample.png
jaraco.imaging-2.1.1.dist-info/LICENSE
jaraco.imaging-2.1.1.dist-info/METADATA
jaraco.imaging-2.1.1.dist-info/WHEEL
jaraco.imaging-2.1.1.dist-info/entry_points.txt
jaraco.imaging-2.1.1.dist-info/top_level.txt
jaraco.imaging-2.1.1.dist-info/RECORD
